pyvisgrid/__init__.py
pyvisgrid/_version.py
pyvisgrid/version.py
pyvisgrid/core/__init__.py
pyvisgrid/core/gridder.py
pyvisgrid/core/stokes.py
pyvisgrid/plotting/__init__.py
pyvisgrid/plotting/plotting.py
pyvisgrid-0.2.0.dist-info/METADATA
pyvisgrid-0.2.0.dist-info/WHEEL
pyvisgrid-0.2.0.dist-info/entry_points.txt
pyvisgrid-0.2.0.dist-info/licenses/LICENSE
pyvisgrid-0.2.0.dist-info/RECORD
